dfsjson/__init__.py
dfsjson/src/__init__.py
dfsjson/src/dfsjson.py
dfsjson-1.1.2.dist-info/LICENSE
dfsjson-1.1.2.dist-info/METADATA
dfsjson-1.1.2.dist-info/WHEEL
dfsjson-1.1.2.dist-info/RECORD
