Metadata-Version: 2.1
Name: dfsjson
Version: 1.1.2
Summary: A robust JSON encoder that fixes errors by utilizing DFS algorithm.
Home-page: https://github.com/AutomaticHourglass/dfsjson
Keywords: JSON,JSON Serialize,DFS,Error correcting JSON
Author: Unsal Gokdag
Author-email: unsal.gokdag@gmail.com
Requires-Python: >=3.8,<4.0
Classifier: Programming Language :: Python :: 3
Classifier: Programming Language :: Python :: 3.8
Classifier: Programming Language :: Python :: 3.9
Classifier: Programming Language :: Python :: 3.10
Classifier: Programming Language :: Python :: 3.11
